pytkas/__init__.py
pytkas/dataframes.py
pytkas/eda.py
pytkas/features.py
pytkas/kaggle.py
pytkas/logging.py
pytkas/modelling.py
pytkas/neural_nets.py
pytkas/nlp.py
pytkas/optuna.py
pytkas/others.py
pytkas/plots.py
pytkas-1.0.0.dist-info/METADATA
pytkas-1.0.0.dist-info/WHEEL
pytkas-1.0.0.dist-info/licenses/LICENSE
pytkas-1.0.0.dist-info/RECORD
