Metadata-Version: 2.3
Name: pytkas
Version: 1.0.0
Summary: PYthon ToolKits and AutomationS (PYTKAS) library containing my classes & UDFs I use during various Data Science and Software Engineering projects
Project-URL: Homepage, https://github.com/markoo26/pytkas
Project-URL: Issues, https://github.com/markoo26/pytkas/issues
Author-email: Marek Pytka <markpyt1992@gmail.com>
License-File: LICENSE
Classifier: License :: OSI Approved :: MIT License
Classifier: Operating System :: OS Independent
Classifier: Programming Language :: Python :: 3
Requires-Python: >=3.8
